COPYING
MANIFEST.in
README.rst
setup.py
tox.ini
omnipresence/__init__.py
omnipresence/case_mapping.py
omnipresence/compat.py
omnipresence/connection.py
omnipresence/hostmask.py
omnipresence/humanize.py
omnipresence/plugin.py
omnipresence/service.py
omnipresence/settings.py
omnipresence.egg-info/PKG-INFO
omnipresence.egg-info/SOURCES.txt
omnipresence.egg-info/dependency_links.txt
omnipresence.egg-info/not-zip-safe
omnipresence.egg-info/requires.txt
omnipresence.egg-info/top_level.txt
omnipresence/message/__init__.py
omnipresence/message/formatting.py
omnipresence/message/parser.py
omnipresence/plugins/__init__.py
omnipresence/plugins/anidb/__init__.py
omnipresence/plugins/anidb/test_anidb.py
omnipresence/plugins/dice/__init__.py
omnipresence/plugins/dice/test_dice.py
omnipresence/plugins/geonames/__init__.py
omnipresence/plugins/google/__init__.py
omnipresence/plugins/google/test_google.py
omnipresence/plugins/help/__init__.py
omnipresence/plugins/help/test_help.py
omnipresence/plugins/more/__init__.py
omnipresence/plugins/more/test_more.py
omnipresence/plugins/url/__init__.py
omnipresence/plugins/url/test_url.py
omnipresence/plugins/vndb/__init__.py
omnipresence/plugins/vndb/test_vndb.py
omnipresence/plugins/wwwjdic/__init__.py
omnipresence/plugins/wwwjdic/test_wwwjdic.py
omnipresence/test/__init__.py
omnipresence/test/helpers.py
omnipresence/test/interactive.py
omnipresence/test/test_case_mapping.py
omnipresence/test/test_command.py
omnipresence/test/test_compat.py
omnipresence/test/test_connection.py
omnipresence/test/test_event.py
omnipresence/test/test_formatting.py
omnipresence/test/test_hostmask.py
omnipresence/test/test_html.py
omnipresence/test/test_http.py
omnipresence/test/test_humanize.py
omnipresence/test/test_message.py
omnipresence/test/test_plugin.py
omnipresence/test/test_settings.py
omnipresence/test/fixtures/cassettes/anidb/multiple-blank-dates.json
omnipresence/test/fixtures/cassettes/anidb/multiple-results.json
omnipresence/test/fixtures/cassettes/anidb/no-results.json
omnipresence/test/fixtures/cassettes/anidb/single-blank-dates.json
omnipresence/test/fixtures/cassettes/anidb/single-result.json
