Metadata-Version: 1.1
Name: omnipresence
Version: 3.0alpha2
Summary: An IRC utility bot
Home-page: https://github.com/kxz/omnipresence
Author: Kevin Xiwei Zheng
Author-email: blankplacement+omnipresence@gmail.com
License: X11
Platform: UNKNOWN
Classifier: Development Status :: 3 - Alpha
Classifier: Framework :: Twisted
Classifier: Intended Audience :: System Administrators
Classifier: License :: OSI Approved :: MIT License
Classifier: Operating System :: OS Independent
Classifier: Programming Language :: Python :: 2
Classifier: Programming Language :: Python :: 2.7
Classifier: Programming Language :: Python :: 2 :: Only
Classifier: Topic :: Communications :: Chat :: Internet Relay Chat
Classifier: Topic :: Software Development :: Libraries :: Application Frameworks
